simplenn/__init__.py
simplenn/block.py
simplenn/network.py
simplenn/activation/__init__.py
simplenn/activation/linear.py
simplenn/activation/relu.py
simplenn/activation/sigmoid.py
simplenn/activation/softmax.py
simplenn/layer/__init__.py
simplenn/layer/dense.py
simplenn/layer/dropout.py
simplenn/layer/layer.py
simplenn/metrics/__init__.py
simplenn/metrics/accuracy.py
simplenn/metrics/auc_prc.py
simplenn/metrics/auc_roc.py
simplenn/metrics/fpr.py
simplenn/metrics/precision.py
simplenn/metrics/tpr.py
simplenn/metrics/loss/__init__.py
simplenn/metrics/loss/binary_cross_entropy.py
simplenn/metrics/loss/categorical_cross_entropy.py
simplenn/metrics/loss/loss.py
simplenn/metrics/loss/mean_absolute_error.py
simplenn/metrics/loss/mean_squared_error.py
simplenn/optimizers/__init__.py
simplenn/optimizers/ada_grad.py
simplenn/optimizers/adam.py
simplenn/optimizers/rms_prop.py
simplenn/optimizers/sgd.py
tests/__init__.py
tests/core/__init__.py
tests/core/test_network.py
simple_neural-0.0.4.dist-info/LICENSE
simple_neural-0.0.4.dist-info/METADATA
simple_neural-0.0.4.dist-info/WHEEL
simple_neural-0.0.4.dist-info/top_level.txt
simple_neural-0.0.4.dist-info/RECORD
